Metadata-Version: 2.1
Name: hosthelp
Version: 2.0.0
Summary: The private helper
Home-page: https://github.com/Anisimov1123/txt2docx/blob/main/README.md?plain=1
Author: Nikita_Anisimov
Author-email: qwerty111111333@mail.ru
License: UNKNOWN
Platform: UNKNOWN
